CHANGES.rst
LICENSE
MANIFEST.in
README.rst
setup.cfg
setup.py
doc/FORMAT.md
doc/env-vars.yaml
doc/exit-codes.yaml
pol.egg-info/PKG-INFO
pol.egg-info/SOURCES.txt
pol.egg-info/dependency_links.txt
pol.egg-info/entry_points.txt
pol.egg-info/not-zip-safe
pol.egg-info/requires.txt
pol.egg-info/top_level.txt
src/__init__.py
src/_version.py
src/blockcipher.py
src/clipboard.py
src/editfile.py
src/elgamal.py
src/envelope.py
src/humanize.py
src/kd.py
src/ks.py
src/main.py
src/parallel.py
src/progressbar.py
src/safe.py
src/serialization.py
src/session.py
src/speed.py
src/terminal.py
src/text.py
src/vi.py
src/xrandom.py
src/editor/__init__.py
src/editor/editfile.vim
src/importers/__init__.py
src/importers/keepass.py
src/importers/psafe3.py
src/passgen/__init__.py
src/passgen/dutch.py
src/passgen/english.py
src/tests/__init__.py
src/tests/test_blockcipher.py
src/tests/test_editfile.py
src/tests/test_elgamal.py
src/tests/test_envelope.py
src/tests/test_import_keepass.py
src/tests/test_import_psafe3.py
src/tests/test_kd.py
src/tests/test_ks.py
src/tests/test_main.py
src/tests/test_progressbar.py
src/tests/test_safe.py
src/tests/test_text.py