Metadata-Version: 1.1
Name: pol
Version: 0.4.0
Summary: pol, a modern password manager
Home-page: https://getpol.org
Author: Bas Westerbaan
Author-email: bas@westerbaan.name
License: GPL 3.0
Platform: UNKNOWN
Classifier: Development Status :: 4 - Beta
Classifier: Environment :: Console
Classifier: License :: OSI Approved :: GNU General Public License v3 (GPLv3)
Classifier: Programming Language :: Python :: 2.6
Classifier: Programming Language :: Python :: 2.7
Classifier: Operating System :: POSIX
Classifier: Topic :: Security
